{
  "lastUpdate": "2025-11-13T19:38:37.415Z",
  "services": {
    "canary-cloud": {
      "status": "operational",
      "lastChecked": "2025-11-13T19:38:37.415Z",
      "responseTime": 186,
      "recentChecks": [
        {
          "timestamp": "2025-11-13T16:25:14.083Z",
          "status": "operational",
          "responseTime": 276,
          "statusCode": 200
        },
        {
          "timestamp": "2025-11-13T16:47:34.209Z",
          "status": "operational",
          "responseTime": 235,
          "statusCode": 200
        },
        {
          "timestamp": "2025-11-13T17:00:03.315Z",
          "status": "operational",
          "responseTime": 332,
          "statusCode": 200
        },
        {
          "timestamp": "2025-11-13T17:26:45.848Z",
          "status": "operational",
          "responseTime": 181,
          "statusCode": 200
        },
        {
          "timestamp": "2025-11-13T17:42:33.148Z",
          "status": "operational",
          "responseTime": 256,
          "statusCode": 200
        },
        {
          "timestamp": "2025-11-13T17:51:59.218Z",
          "status": "operational",
          "responseTime": 220,
          "statusCode": 200
        },
        {
          "timestamp": "2025-11-13T18:13:04.677Z",
          "status": "operational",
          "responseTime": 269,
          "statusCode": 200
        },
        {
          "timestamp": "2025-11-13T18:44:23.090Z",
          "status": "operational",
          "responseTime": 209,
          "statusCode": 200
        },
        {
          "timestamp": "2025-11-13T18:57:32.807Z",
          "status": "operational",
          "responseTime": 276,
          "statusCode": 200
        },
        {
          "timestamp": "2025-11-13T19:17:59.654Z",
          "status": "operational",
          "responseTime": 223,
          "statusCode": 200
        },
        {
          "timestamp": "2025-11-13T19:28:11.380Z",
          "status": "operational",
          "responseTime": 287,
          "statusCode": 200
        },
        {
          "timestamp": "2025-11-13T19:38:37.415Z",
          "status": "operational",
          "responseTime": 186,
          "statusCode": 200
        }
      ]
    },
    "character-wiki": {
      "status": "operational",
      "lastChecked": "2025-11-13T19:38:37.415Z",
      "responseTime": 652,
      "recentChecks": [
        {
          "timestamp": "2025-11-13T16:25:14.083Z",
          "status": "operational",
          "responseTime": 713,
          "statusCode": 301
        },
        {
          "timestamp": "2025-11-13T16:47:34.209Z",
          "status": "operational",
          "responseTime": 414,
          "statusCode": 301
        },
        {
          "timestamp": "2025-11-13T17:00:03.315Z",
          "status": "operational",
          "responseTime": 542,
          "statusCode": 301
        },
        {
          "timestamp": "2025-11-13T17:26:45.848Z",
          "status": "operational",
          "responseTime": 473,
          "statusCode": 301
        },
        {
          "timestamp": "2025-11-13T17:42:33.148Z",
          "status": "operational",
          "responseTime": 420,
          "statusCode": 301
        },
        {
          "timestamp": "2025-11-13T17:51:59.218Z",
          "status": "operational",
          "responseTime": 347,
          "statusCode": 301
        },
        {
          "timestamp": "2025-11-13T18:13:04.677Z",
          "status": "operational",
          "responseTime": 363,
          "statusCode": 301
        },
        {
          "timestamp": "2025-11-13T18:44:23.090Z",
          "status": "operational",
          "responseTime": 422,
          "statusCode": 301
        },
        {
          "timestamp": "2025-11-13T18:57:32.807Z",
          "status": "operational",
          "responseTime": 554,
          "statusCode": 301
        },
        {
          "timestamp": "2025-11-13T19:17:59.654Z",
          "status": "operational",
          "responseTime": 469,
          "statusCode": 301
        },
        {
          "timestamp": "2025-11-13T19:28:11.380Z",
          "status": "operational",
          "responseTime": 1572,
          "statusCode": 301
        },
        {
          "timestamp": "2025-11-13T19:38:37.415Z",
          "status": "operational",
          "responseTime": 652,
          "statusCode": 301
        }
      ]
    }
  }
}