{
  "lastUpdate": "2025-10-30T11:26:40.214Z",
  "services": {
    "canary-cloud": {
      "status": "operational",
      "lastChecked": "2025-10-30T11:26:40.214Z",
      "responseTime": 349,
      "recentChecks": [
        {
          "timestamp": "2025-10-30T08:15:01.227Z",
          "status": "operational",
          "responseTime": 335,
          "statusCode": 200
        },
        {
          "timestamp": "2025-10-30T08:42:19.887Z",
          "status": "operational",
          "responseTime": 257,
          "statusCode": 200
        },
        {
          "timestamp": "2025-10-30T08:55:50.956Z",
          "status": "operational",
          "responseTime": 198,
          "statusCode": 200
        },
        {
          "timestamp": "2025-10-30T09:19:09.714Z",
          "status": "operational",
          "responseTime": 276,
          "statusCode": 200
        },
        {
          "timestamp": "2025-10-30T09:37:36.460Z",
          "status": "operational",
          "responseTime": 270,
          "statusCode": 200
        },
        {
          "timestamp": "2025-10-30T09:48:40.129Z",
          "status": "operational",
          "responseTime": 364,
          "statusCode": 200
        },
        {
          "timestamp": "2025-10-30T09:57:26.735Z",
          "status": "operational",
          "responseTime": 272,
          "statusCode": 200
        },
        {
          "timestamp": "2025-10-30T10:23:08.267Z",
          "status": "operational",
          "responseTime": 326,
          "statusCode": 200
        },
        {
          "timestamp": "2025-10-30T10:41:58.238Z",
          "status": "operational",
          "responseTime": 259,
          "statusCode": 200
        },
        {
          "timestamp": "2025-10-30T10:52:41.041Z",
          "status": "operational",
          "responseTime": 207,
          "statusCode": 200
        },
        {
          "timestamp": "2025-10-30T11:09:33.275Z",
          "status": "operational",
          "responseTime": 272,
          "statusCode": 200
        },
        {
          "timestamp": "2025-10-30T11:26:40.214Z",
          "status": "operational",
          "responseTime": 349,
          "statusCode": 200
        }
      ]
    },
    "character-wiki": {
      "status": "operational",
      "lastChecked": "2025-10-30T11:26:40.214Z",
      "responseTime": 481,
      "recentChecks": [
        {
          "timestamp": "2025-10-30T08:15:01.227Z",
          "status": "operational",
          "responseTime": 426,
          "statusCode": 301
        },
        {
          "timestamp": "2025-10-30T08:42:19.887Z",
          "status": "operational",
          "responseTime": 485,
          "statusCode": 301
        },
        {
          "timestamp": "2025-10-30T08:55:50.956Z",
          "status": "operational",
          "responseTime": 537,
          "statusCode": 301
        },
        {
          "timestamp": "2025-10-30T09:19:09.714Z",
          "status": "operational",
          "responseTime": 323,
          "statusCode": 301
        },
        {
          "timestamp": "2025-10-30T09:37:36.460Z",
          "status": "operational",
          "responseTime": 500,
          "statusCode": 301
        },
        {
          "timestamp": "2025-10-30T09:48:40.129Z",
          "status": "operational",
          "responseTime": 601,
          "statusCode": 301
        },
        {
          "timestamp": "2025-10-30T09:57:26.735Z",
          "status": "operational",
          "responseTime": 395,
          "statusCode": 301
        },
        {
          "timestamp": "2025-10-30T10:23:08.267Z",
          "status": "operational",
          "responseTime": 2451,
          "statusCode": 301
        },
        {
          "timestamp": "2025-10-30T10:41:58.238Z",
          "status": "operational",
          "responseTime": 479,
          "statusCode": 301
        },
        {
          "timestamp": "2025-10-30T10:52:41.041Z",
          "status": "operational",
          "responseTime": 372,
          "statusCode": 301
        },
        {
          "timestamp": "2025-10-30T11:09:33.275Z",
          "status": "operational",
          "responseTime": 501,
          "statusCode": 301
        },
        {
          "timestamp": "2025-10-30T11:26:40.214Z",
          "status": "operational",
          "responseTime": 481,
          "statusCode": 301
        }
      ]
    }
  }
}