{
  "lastUpdate": "2025-10-29T17:49:32.965Z",
  "services": {
    "canary-cloud": {
      "status": "operational",
      "lastChecked": "2025-10-29T17:49:32.965Z",
      "responseTime": 369,
      "recentChecks": [
        {
          "timestamp": "2025-10-29T14:16:08.274Z",
          "status": "operational",
          "responseTime": 414,
          "statusCode": 200
        },
        {
          "timestamp": "2025-10-29T14:40:27.503Z",
          "status": "operational",
          "responseTime": 352,
          "statusCode": 200
        },
        {
          "timestamp": "2025-10-29T14:54:01.825Z",
          "status": "operational",
          "responseTime": 306,
          "statusCode": 200
        },
        {
          "timestamp": "2025-10-29T15:16:10.160Z",
          "status": "operational",
          "responseTime": 314,
          "statusCode": 200
        },
        {
          "timestamp": "2025-10-29T15:38:31.768Z",
          "status": "operational",
          "responseTime": 330,
          "statusCode": 200
        },
        {
          "timestamp": "2025-10-29T15:52:16.606Z",
          "status": "operational",
          "responseTime": 471,
          "statusCode": 200
        },
        {
          "timestamp": "2025-10-29T16:12:20.542Z",
          "status": "operational",
          "responseTime": 194,
          "statusCode": 200
        },
        {
          "timestamp": "2025-10-29T16:43:48.034Z",
          "status": "operational",
          "responseTime": 339,
          "statusCode": 200
        },
        {
          "timestamp": "2025-10-29T16:58:27.946Z",
          "status": "operational",
          "responseTime": 321,
          "statusCode": 200
        },
        {
          "timestamp": "2025-10-29T17:22:36.821Z",
          "status": "operational",
          "responseTime": 218,
          "statusCode": 200
        },
        {
          "timestamp": "2025-10-29T17:39:44.467Z",
          "status": "operational",
          "responseTime": 364,
          "statusCode": 200
        },
        {
          "timestamp": "2025-10-29T17:49:32.965Z",
          "status": "operational",
          "responseTime": 369,
          "statusCode": 200
        }
      ]
    },
    "character-wiki": {
      "status": "operational",
      "lastChecked": "2025-10-29T17:49:32.965Z",
      "responseTime": 399,
      "recentChecks": [
        {
          "timestamp": "2025-10-29T14:16:08.274Z",
          "status": "operational",
          "responseTime": 666,
          "statusCode": 301
        },
        {
          "timestamp": "2025-10-29T14:40:27.503Z",
          "status": "operational",
          "responseTime": 385,
          "statusCode": 301
        },
        {
          "timestamp": "2025-10-29T14:54:01.825Z",
          "status": "operational",
          "responseTime": 527,
          "statusCode": 301
        },
        {
          "timestamp": "2025-10-29T15:16:10.160Z",
          "status": "operational",
          "responseTime": 338,
          "statusCode": 301
        },
        {
          "timestamp": "2025-10-29T15:38:31.768Z",
          "status": "operational",
          "responseTime": 645,
          "statusCode": 301
        },
        {
          "timestamp": "2025-10-29T15:52:16.606Z",
          "status": "operational",
          "responseTime": 487,
          "statusCode": 301
        },
        {
          "timestamp": "2025-10-29T16:12:20.542Z",
          "status": "operational",
          "responseTime": 482,
          "statusCode": 301
        },
        {
          "timestamp": "2025-10-29T16:43:48.034Z",
          "status": "operational",
          "responseTime": 475,
          "statusCode": 301
        },
        {
          "timestamp": "2025-10-29T16:58:27.946Z",
          "status": "operational",
          "responseTime": 333,
          "statusCode": 301
        },
        {
          "timestamp": "2025-10-29T17:22:36.821Z",
          "status": "operational",
          "responseTime": 515,
          "statusCode": 301
        },
        {
          "timestamp": "2025-10-29T17:39:44.467Z",
          "status": "operational",
          "responseTime": 477,
          "statusCode": 301
        },
        {
          "timestamp": "2025-10-29T17:49:32.965Z",
          "status": "operational",
          "responseTime": 399,
          "statusCode": 301
        }
      ]
    }
  }
}