{
  "lastUpdate": "2025-11-11T16:47:55.969Z",
  "services": {
    "canary-cloud": {
      "status": "operational",
      "lastChecked": "2025-11-11T16:47:55.969Z",
      "responseTime": 293,
      "recentChecks": [
        {
          "timestamp": "2025-11-11T13:22:38.008Z",
          "status": "operational",
          "responseTime": 284,
          "statusCode": 200
        },
        {
          "timestamp": "2025-11-11T13:45:18.838Z",
          "status": "operational",
          "responseTime": 218,
          "statusCode": 200
        },
        {
          "timestamp": "2025-11-11T13:55:24.458Z",
          "status": "operational",
          "responseTime": 293,
          "statusCode": 200
        },
        {
          "timestamp": "2025-11-11T14:18:02.803Z",
          "status": "operational",
          "responseTime": 263,
          "statusCode": 200
        },
        {
          "timestamp": "2025-11-11T14:40:00.547Z",
          "status": "operational",
          "responseTime": 199,
          "statusCode": 200
        },
        {
          "timestamp": "2025-11-11T14:52:41.414Z",
          "status": "operational",
          "responseTime": 103,
          "statusCode": 200
        },
        {
          "timestamp": "2025-11-11T15:11:33.035Z",
          "status": "operational",
          "responseTime": 381,
          "statusCode": 200
        },
        {
          "timestamp": "2025-11-11T15:33:50.405Z",
          "status": "operational",
          "responseTime": 234,
          "statusCode": 200
        },
        {
          "timestamp": "2025-11-11T15:46:56.705Z",
          "status": "operational",
          "responseTime": 261,
          "statusCode": 200
        },
        {
          "timestamp": "2025-11-11T15:56:18.516Z",
          "status": "operational",
          "responseTime": 170,
          "statusCode": 200
        },
        {
          "timestamp": "2025-11-11T16:24:54.373Z",
          "status": "operational",
          "responseTime": 337,
          "statusCode": 200
        },
        {
          "timestamp": "2025-11-11T16:47:55.969Z",
          "status": "operational",
          "responseTime": 293,
          "statusCode": 200
        }
      ]
    },
    "character-wiki": {
      "status": "operational",
      "lastChecked": "2025-11-11T16:47:55.969Z",
      "responseTime": 773,
      "recentChecks": [
        {
          "timestamp": "2025-11-11T13:22:38.008Z",
          "status": "operational",
          "responseTime": 329,
          "statusCode": 301
        },
        {
          "timestamp": "2025-11-11T13:45:18.838Z",
          "status": "operational",
          "responseTime": 503,
          "statusCode": 301
        },
        {
          "timestamp": "2025-11-11T13:55:24.458Z",
          "status": "operational",
          "responseTime": 856,
          "statusCode": 301
        },
        {
          "timestamp": "2025-11-11T14:18:02.803Z",
          "status": "operational",
          "responseTime": 457,
          "statusCode": 301
        },
        {
          "timestamp": "2025-11-11T14:40:00.547Z",
          "status": "operational",
          "responseTime": 1899,
          "statusCode": 301
        },
        {
          "timestamp": "2025-11-11T14:52:41.414Z",
          "status": "operational",
          "responseTime": 521,
          "statusCode": 301
        },
        {
          "timestamp": "2025-11-11T15:11:33.035Z",
          "status": "operational",
          "responseTime": 464,
          "statusCode": 301
        },
        {
          "timestamp": "2025-11-11T15:33:50.405Z",
          "status": "operational",
          "responseTime": 432,
          "statusCode": 301
        },
        {
          "timestamp": "2025-11-11T15:46:56.705Z",
          "status": "operational",
          "responseTime": 455,
          "statusCode": 301
        },
        {
          "timestamp": "2025-11-11T15:56:18.516Z",
          "status": "operational",
          "responseTime": 1409,
          "statusCode": 301
        },
        {
          "timestamp": "2025-11-11T16:24:54.373Z",
          "status": "operational",
          "responseTime": 555,
          "statusCode": 301
        },
        {
          "timestamp": "2025-11-11T16:47:55.969Z",
          "status": "operational",
          "responseTime": 773,
          "statusCode": 301
        }
      ]
    }
  }
}