{
  "lastUpdate": "2025-10-31T09:52:32.473Z",
  "services": {
    "canary-cloud": {
      "status": "operational",
      "lastChecked": "2025-10-31T09:52:32.473Z",
      "responseTime": 345,
      "recentChecks": [
        {
          "timestamp": "2025-10-31T06:54:46.038Z",
          "status": "operational",
          "responseTime": 221,
          "statusCode": 200
        },
        {
          "timestamp": "2025-10-31T07:14:21.616Z",
          "status": "operational",
          "responseTime": 253,
          "statusCode": 200
        },
        {
          "timestamp": "2025-10-31T07:30:18.879Z",
          "status": "operational",
          "responseTime": 290,
          "statusCode": 200
        },
        {
          "timestamp": "2025-10-31T07:41:23.591Z",
          "status": "operational",
          "responseTime": 275,
          "statusCode": 200
        },
        {
          "timestamp": "2025-10-31T07:50:53.047Z",
          "status": "operational",
          "responseTime": 192,
          "statusCode": 200
        },
        {
          "timestamp": "2025-10-31T08:00:07.685Z",
          "status": "operational",
          "responseTime": 293,
          "statusCode": 200
        },
        {
          "timestamp": "2025-10-31T08:34:34.344Z",
          "status": "operational",
          "responseTime": 333,
          "statusCode": 200
        },
        {
          "timestamp": "2025-10-31T08:51:18.578Z",
          "status": "operational",
          "responseTime": 226,
          "statusCode": 200
        },
        {
          "timestamp": "2025-10-31T09:00:43.506Z",
          "status": "operational",
          "responseTime": 295,
          "statusCode": 200
        },
        {
          "timestamp": "2025-10-31T09:29:13.798Z",
          "status": "operational",
          "responseTime": 330,
          "statusCode": 200
        },
        {
          "timestamp": "2025-10-31T09:43:10.958Z",
          "status": "operational",
          "responseTime": 256,
          "statusCode": 200
        },
        {
          "timestamp": "2025-10-31T09:52:32.473Z",
          "status": "operational",
          "responseTime": 345,
          "statusCode": 200
        }
      ]
    },
    "character-wiki": {
      "status": "operational",
      "lastChecked": "2025-10-31T09:52:32.473Z",
      "responseTime": 488,
      "recentChecks": [
        {
          "timestamp": "2025-10-31T06:54:46.038Z",
          "status": "operational",
          "responseTime": 480,
          "statusCode": 301
        },
        {
          "timestamp": "2025-10-31T07:14:21.616Z",
          "status": "operational",
          "responseTime": 492,
          "statusCode": 301
        },
        {
          "timestamp": "2025-10-31T07:30:18.879Z",
          "status": "operational",
          "responseTime": 390,
          "statusCode": 301
        },
        {
          "timestamp": "2025-10-31T07:41:23.591Z",
          "status": "operational",
          "responseTime": 522,
          "statusCode": 301
        },
        {
          "timestamp": "2025-10-31T07:50:53.047Z",
          "status": "operational",
          "responseTime": 525,
          "statusCode": 301
        },
        {
          "timestamp": "2025-10-31T08:00:07.685Z",
          "status": "operational",
          "responseTime": 452,
          "statusCode": 301
        },
        {
          "timestamp": "2025-10-31T08:34:34.344Z",
          "status": "operational",
          "responseTime": 468,
          "statusCode": 301
        },
        {
          "timestamp": "2025-10-31T08:51:18.578Z",
          "status": "degraded",
          "responseTime": 339,
          "statusCode": 502
        },
        {
          "timestamp": "2025-10-31T09:00:43.506Z",
          "status": "down",
          "responseTime": 10245
        },
        {
          "timestamp": "2025-10-31T09:29:13.798Z",
          "status": "operational",
          "responseTime": 509,
          "statusCode": 301
        },
        {
          "timestamp": "2025-10-31T09:43:10.958Z",
          "status": "operational",
          "responseTime": 395,
          "statusCode": 301
        },
        {
          "timestamp": "2025-10-31T09:52:32.473Z",
          "status": "operational",
          "responseTime": 488,
          "statusCode": 301
        }
      ]
    }
  }
}