{
  "lastUpdate": "2025-11-13T07:44:32.924Z",
  "services": {
    "canary-cloud": {
      "status": "operational",
      "lastChecked": "2025-11-13T07:44:32.924Z",
      "responseTime": 325,
      "recentChecks": [
        {
          "timestamp": "2025-11-13T04:33:13.898Z",
          "status": "operational",
          "responseTime": 381,
          "statusCode": 200
        },
        {
          "timestamp": "2025-11-13T04:48:29.704Z",
          "status": "operational",
          "responseTime": 179,
          "statusCode": 200
        },
        {
          "timestamp": "2025-11-13T04:57:53.362Z",
          "status": "operational",
          "responseTime": 296,
          "statusCode": 200
        },
        {
          "timestamp": "2025-11-13T05:23:07.528Z",
          "status": "operational",
          "responseTime": 260,
          "statusCode": 200
        },
        {
          "timestamp": "2025-11-13T05:40:26.803Z",
          "status": "operational",
          "responseTime": 290,
          "statusCode": 200
        },
        {
          "timestamp": "2025-11-13T05:50:26.545Z",
          "status": "operational",
          "responseTime": 300,
          "statusCode": 200
        },
        {
          "timestamp": "2025-11-13T05:59:33.317Z",
          "status": "operational",
          "responseTime": 203,
          "statusCode": 200
        },
        {
          "timestamp": "2025-11-13T06:39:53.771Z",
          "status": "operational",
          "responseTime": 308,
          "statusCode": 200
        },
        {
          "timestamp": "2025-11-13T06:56:32.918Z",
          "status": "operational",
          "responseTime": 178,
          "statusCode": 200
        },
        {
          "timestamp": "2025-11-13T07:19:23.161Z",
          "status": "operational",
          "responseTime": 324,
          "statusCode": 200
        },
        {
          "timestamp": "2025-11-13T07:34:38.547Z",
          "status": "operational",
          "responseTime": 319,
          "statusCode": 200
        },
        {
          "timestamp": "2025-11-13T07:44:32.924Z",
          "status": "operational",
          "responseTime": 325,
          "statusCode": 200
        }
      ]
    },
    "character-wiki": {
      "status": "operational",
      "lastChecked": "2025-11-13T07:44:32.924Z",
      "responseTime": 460,
      "recentChecks": [
        {
          "timestamp": "2025-11-13T04:33:13.898Z",
          "status": "operational",
          "responseTime": 541,
          "statusCode": 301
        },
        {
          "timestamp": "2025-11-13T04:48:29.704Z",
          "status": "operational",
          "responseTime": 489,
          "statusCode": 301
        },
        {
          "timestamp": "2025-11-13T04:57:53.362Z",
          "status": "operational",
          "responseTime": 500,
          "statusCode": 301
        },
        {
          "timestamp": "2025-11-13T05:23:07.528Z",
          "status": "operational",
          "responseTime": 557,
          "statusCode": 301
        },
        {
          "timestamp": "2025-11-13T05:40:26.803Z",
          "status": "operational",
          "responseTime": 656,
          "statusCode": 301
        },
        {
          "timestamp": "2025-11-13T05:50:26.545Z",
          "status": "operational",
          "responseTime": 363,
          "statusCode": 301
        },
        {
          "timestamp": "2025-11-13T05:59:33.317Z",
          "status": "operational",
          "responseTime": 564,
          "statusCode": 301
        },
        {
          "timestamp": "2025-11-13T06:39:53.771Z",
          "status": "operational",
          "responseTime": 882,
          "statusCode": 301
        },
        {
          "timestamp": "2025-11-13T06:56:32.918Z",
          "status": "operational",
          "responseTime": 476,
          "statusCode": 301
        },
        {
          "timestamp": "2025-11-13T07:19:23.161Z",
          "status": "operational",
          "responseTime": 437,
          "statusCode": 301
        },
        {
          "timestamp": "2025-11-13T07:34:38.547Z",
          "status": "operational",
          "responseTime": 358,
          "statusCode": 301
        },
        {
          "timestamp": "2025-11-13T07:44:32.924Z",
          "status": "operational",
          "responseTime": 460,
          "statusCode": 301
        }
      ]
    }
  }
}