{
  "lastUpdate": "2025-11-15T13:59:01.591Z",
  "services": {
    "canary-cloud": {
      "status": "operational",
      "lastChecked": "2025-11-15T13:59:01.591Z",
      "responseTime": 191,
      "recentChecks": [
        {
          "timestamp": "2025-11-15T10:55:41.764Z",
          "status": "operational",
          "responseTime": 250,
          "statusCode": 200
        },
        {
          "timestamp": "2025-11-15T11:12:56.155Z",
          "status": "operational",
          "responseTime": 286,
          "statusCode": 200
        },
        {
          "timestamp": "2025-11-15T11:25:35.591Z",
          "status": "operational",
          "responseTime": 333,
          "statusCode": 200
        },
        {
          "timestamp": "2025-11-15T11:36:25.676Z",
          "status": "operational",
          "responseTime": 285,
          "statusCode": 200
        },
        {
          "timestamp": "2025-11-15T11:45:25.714Z",
          "status": "operational",
          "responseTime": 415,
          "statusCode": 200
        },
        {
          "timestamp": "2025-11-15T11:54:00.169Z",
          "status": "operational",
          "responseTime": 322,
          "statusCode": 200
        },
        {
          "timestamp": "2025-11-15T12:23:59.611Z",
          "status": "operational",
          "responseTime": 309,
          "statusCode": 200
        },
        {
          "timestamp": "2025-11-15T12:59:15.010Z",
          "status": "operational",
          "responseTime": 276,
          "statusCode": 200
        },
        {
          "timestamp": "2025-11-15T13:28:59.160Z",
          "status": "operational",
          "responseTime": 282,
          "statusCode": 200
        },
        {
          "timestamp": "2025-11-15T13:41:33.112Z",
          "status": "operational",
          "responseTime": 327,
          "statusCode": 200
        },
        {
          "timestamp": "2025-11-15T13:50:21.892Z",
          "status": "operational",
          "responseTime": 195,
          "statusCode": 200
        },
        {
          "timestamp": "2025-11-15T13:59:01.591Z",
          "status": "operational",
          "responseTime": 191,
          "statusCode": 200
        }
      ]
    },
    "character-wiki": {
      "status": "operational",
      "lastChecked": "2025-11-15T13:59:01.591Z",
      "responseTime": 510,
      "recentChecks": [
        {
          "timestamp": "2025-11-15T10:55:41.764Z",
          "status": "operational",
          "responseTime": 489,
          "statusCode": 301
        },
        {
          "timestamp": "2025-11-15T11:12:56.155Z",
          "status": "operational",
          "responseTime": 462,
          "statusCode": 301
        },
        {
          "timestamp": "2025-11-15T11:25:35.591Z",
          "status": "operational",
          "responseTime": 471,
          "statusCode": 301
        },
        {
          "timestamp": "2025-11-15T11:36:25.676Z",
          "status": "operational",
          "responseTime": 451,
          "statusCode": 301
        },
        {
          "timestamp": "2025-11-15T11:45:25.714Z",
          "status": "operational",
          "responseTime": 432,
          "statusCode": 301
        },
        {
          "timestamp": "2025-11-15T11:54:00.169Z",
          "status": "operational",
          "responseTime": 418,
          "statusCode": 301
        },
        {
          "timestamp": "2025-11-15T12:23:59.611Z",
          "status": "operational",
          "responseTime": 1740,
          "statusCode": 301
        },
        {
          "timestamp": "2025-11-15T12:59:15.010Z",
          "status": "operational",
          "responseTime": 469,
          "statusCode": 301
        },
        {
          "timestamp": "2025-11-15T13:28:59.160Z",
          "status": "operational",
          "responseTime": 460,
          "statusCode": 301
        },
        {
          "timestamp": "2025-11-15T13:41:33.112Z",
          "status": "operational",
          "responseTime": 483,
          "statusCode": 301
        },
        {
          "timestamp": "2025-11-15T13:50:21.892Z",
          "status": "operational",
          "responseTime": 599,
          "statusCode": 301
        },
        {
          "timestamp": "2025-11-15T13:59:01.591Z",
          "status": "operational",
          "responseTime": 510,
          "statusCode": 301
        }
      ]
    }
  }
}