{
  "lastUpdate": "2025-10-24T14:26:21.503Z",
  "services": {
    "canary-cloud": {
      "status": "down",
      "lastChecked": "2025-10-24T14:26:21.503Z",
      "responseTime": 10532,
      "recentChecks": [
        {
          "timestamp": "2025-10-24T10:51:28.776Z",
          "status": "down",
          "responseTime": 10175
        },
        {
          "timestamp": "2025-10-24T11:00:19.032Z",
          "status": "down",
          "responseTime": 10209
        },
        {
          "timestamp": "2025-10-24T11:23:33.176Z",
          "status": "down",
          "responseTime": 10216
        },
        {
          "timestamp": "2025-10-24T11:35:27.890Z",
          "status": "down",
          "responseTime": 10189
        },
        {
          "timestamp": "2025-10-24T11:44:54.529Z",
          "status": "down",
          "responseTime": 10243
        },
        {
          "timestamp": "2025-10-24T11:53:55.549Z",
          "status": "down",
          "responseTime": 10372
        },
        {
          "timestamp": "2025-10-24T12:27:35.015Z",
          "status": "down",
          "responseTime": 11310
        },
        {
          "timestamp": "2025-10-24T13:07:11.602Z",
          "status": "down",
          "responseTime": 10213
        },
        {
          "timestamp": "2025-10-24T13:39:57.556Z",
          "status": "down",
          "responseTime": 10208
        },
        {
          "timestamp": "2025-10-24T13:50:26.741Z",
          "status": "down",
          "responseTime": 10171
        },
        {
          "timestamp": "2025-10-24T13:59:16.122Z",
          "status": "down",
          "responseTime": 10267
        },
        {
          "timestamp": "2025-10-24T14:26:21.503Z",
          "status": "down",
          "responseTime": 10532
        }
      ]
    },
    "character-wiki": {
      "status": "operational",
      "lastChecked": "2025-10-24T14:26:21.503Z",
      "responseTime": 421,
      "recentChecks": [
        {
          "timestamp": "2025-10-24T10:51:28.776Z",
          "status": "operational",
          "responseTime": 549,
          "statusCode": 301
        },
        {
          "timestamp": "2025-10-24T11:00:19.032Z",
          "status": "operational",
          "responseTime": 575,
          "statusCode": 301
        },
        {
          "timestamp": "2025-10-24T11:23:33.176Z",
          "status": "operational",
          "responseTime": 451,
          "statusCode": 301
        },
        {
          "timestamp": "2025-10-24T11:35:27.890Z",
          "status": "operational",
          "responseTime": 366,
          "statusCode": 301
        },
        {
          "timestamp": "2025-10-24T11:44:54.529Z",
          "status": "operational",
          "responseTime": 489,
          "statusCode": 301
        },
        {
          "timestamp": "2025-10-24T11:53:55.549Z",
          "status": "operational",
          "responseTime": 390,
          "statusCode": 301
        },
        {
          "timestamp": "2025-10-24T12:27:35.015Z",
          "status": "operational",
          "responseTime": 495,
          "statusCode": 301
        },
        {
          "timestamp": "2025-10-24T13:07:11.602Z",
          "status": "operational",
          "responseTime": 437,
          "statusCode": 301
        },
        {
          "timestamp": "2025-10-24T13:39:57.556Z",
          "status": "operational",
          "responseTime": 477,
          "statusCode": 301
        },
        {
          "timestamp": "2025-10-24T13:50:26.741Z",
          "status": "operational",
          "responseTime": 581,
          "statusCode": 301
        },
        {
          "timestamp": "2025-10-24T13:59:16.122Z",
          "status": "operational",
          "responseTime": 472,
          "statusCode": 301
        },
        {
          "timestamp": "2025-10-24T14:26:21.503Z",
          "status": "operational",
          "responseTime": 421,
          "statusCode": 301
        }
      ]
    }
  }
}