{
  "lastUpdate": "2025-11-14T04:27:36.304Z",
  "services": {
    "canary-cloud": {
      "status": "operational",
      "lastChecked": "2025-11-14T04:27:36.304Z",
      "responseTime": 276,
      "recentChecks": [
        {
          "timestamp": "2025-11-13T22:36:47.020Z",
          "status": "operational",
          "responseTime": 326,
          "statusCode": 200
        },
        {
          "timestamp": "2025-11-13T22:46:02.761Z",
          "status": "operational",
          "responseTime": 329,
          "statusCode": 200
        },
        {
          "timestamp": "2025-11-13T22:54:52.807Z",
          "status": "operational",
          "responseTime": 422,
          "statusCode": 200
        },
        {
          "timestamp": "2025-11-13T23:15:22.770Z",
          "status": "operational",
          "responseTime": 285,
          "statusCode": 200
        },
        {
          "timestamp": "2025-11-13T23:31:25.141Z",
          "status": "operational",
          "responseTime": 216,
          "statusCode": 200
        },
        {
          "timestamp": "2025-11-13T23:42:34.526Z",
          "status": "operational",
          "responseTime": 348,
          "statusCode": 200
        },
        {
          "timestamp": "2025-11-13T23:51:44.543Z",
          "status": "operational",
          "responseTime": 849,
          "statusCode": 200
        },
        {
          "timestamp": "2025-11-14T00:42:35.827Z",
          "status": "operational",
          "responseTime": 371,
          "statusCode": 200
        },
        {
          "timestamp": "2025-11-14T02:23:09.469Z",
          "status": "operational",
          "responseTime": 186,
          "statusCode": 200
        },
        {
          "timestamp": "2025-11-14T03:32:06.607Z",
          "status": "operational",
          "responseTime": 236,
          "statusCode": 200
        },
        {
          "timestamp": "2025-11-14T03:58:09.037Z",
          "status": "operational",
          "responseTime": 320,
          "statusCode": 200
        },
        {
          "timestamp": "2025-11-14T04:27:36.304Z",
          "status": "operational",
          "responseTime": 276,
          "statusCode": 200
        }
      ]
    },
    "character-wiki": {
      "status": "operational",
      "lastChecked": "2025-11-14T04:27:36.304Z",
      "responseTime": 398,
      "recentChecks": [
        {
          "timestamp": "2025-11-13T22:36:47.020Z",
          "status": "operational",
          "responseTime": 471,
          "statusCode": 301
        },
        {
          "timestamp": "2025-11-13T22:46:02.761Z",
          "status": "operational",
          "responseTime": 451,
          "statusCode": 301
        },
        {
          "timestamp": "2025-11-13T22:54:52.807Z",
          "status": "operational",
          "responseTime": 897,
          "statusCode": 301
        },
        {
          "timestamp": "2025-11-13T23:15:22.770Z",
          "status": "operational",
          "responseTime": 490,
          "statusCode": 301
        },
        {
          "timestamp": "2025-11-13T23:31:25.141Z",
          "status": "operational",
          "responseTime": 5041,
          "statusCode": 301
        },
        {
          "timestamp": "2025-11-13T23:42:34.526Z",
          "status": "operational",
          "responseTime": 683,
          "statusCode": 301
        },
        {
          "timestamp": "2025-11-13T23:51:44.543Z",
          "status": "operational",
          "responseTime": 2408,
          "statusCode": 301
        },
        {
          "timestamp": "2025-11-14T00:42:35.827Z",
          "status": "degraded",
          "responseTime": 463,
          "statusCode": 502
        },
        {
          "timestamp": "2025-11-14T02:23:09.469Z",
          "status": "operational",
          "responseTime": 567,
          "statusCode": 301
        },
        {
          "timestamp": "2025-11-14T03:32:06.607Z",
          "status": "operational",
          "responseTime": 474,
          "statusCode": 301
        },
        {
          "timestamp": "2025-11-14T03:58:09.037Z",
          "status": "operational",
          "responseTime": 341,
          "statusCode": 301
        },
        {
          "timestamp": "2025-11-14T04:27:36.304Z",
          "status": "operational",
          "responseTime": 398,
          "statusCode": 301
        }
      ]
    }
  }
}