{
  "lastUpdate": "2025-10-26T04:59:40.813Z",
  "services": {
    "canary-cloud": {
      "status": "operational",
      "lastChecked": "2025-10-26T04:59:40.813Z",
      "responseTime": 231,
      "recentChecks": [
        {
          "timestamp": "2025-10-25T23:30:33.588Z",
          "status": "operational",
          "responseTime": 354,
          "statusCode": 200
        },
        {
          "timestamp": "2025-10-25T23:40:31.024Z",
          "status": "operational",
          "responseTime": 307,
          "statusCode": 200
        },
        {
          "timestamp": "2025-10-25T23:49:52.523Z",
          "status": "operational",
          "responseTime": 239,
          "statusCode": 200
        },
        {
          "timestamp": "2025-10-25T23:59:12.498Z",
          "status": "operational",
          "responseTime": 337,
          "statusCode": 200
        },
        {
          "timestamp": "2025-10-26T02:02:47.589Z",
          "status": "operational",
          "responseTime": 314,
          "statusCode": 200
        },
        {
          "timestamp": "2025-10-26T03:15:21.899Z",
          "status": "operational",
          "responseTime": 385,
          "statusCode": 200
        },
        {
          "timestamp": "2025-10-26T03:48:23.583Z",
          "status": "operational",
          "responseTime": 321,
          "statusCode": 200
        },
        {
          "timestamp": "2025-10-26T03:58:58.162Z",
          "status": "operational",
          "responseTime": 340,
          "statusCode": 200
        },
        {
          "timestamp": "2025-10-26T04:27:13.425Z",
          "status": "operational",
          "responseTime": 351,
          "statusCode": 200
        },
        {
          "timestamp": "2025-10-26T04:42:06.079Z",
          "status": "operational",
          "responseTime": 312,
          "statusCode": 200
        },
        {
          "timestamp": "2025-10-26T04:51:07.018Z",
          "status": "operational",
          "responseTime": 344,
          "statusCode": 200
        },
        {
          "timestamp": "2025-10-26T04:59:40.813Z",
          "status": "operational",
          "responseTime": 231,
          "statusCode": 200
        }
      ]
    },
    "character-wiki": {
      "status": "operational",
      "lastChecked": "2025-10-26T04:59:40.813Z",
      "responseTime": 344,
      "recentChecks": [
        {
          "timestamp": "2025-10-25T23:30:33.588Z",
          "status": "operational",
          "responseTime": 242,
          "statusCode": 301
        },
        {
          "timestamp": "2025-10-25T23:40:31.024Z",
          "status": "operational",
          "responseTime": 495,
          "statusCode": 301
        },
        {
          "timestamp": "2025-10-25T23:49:52.523Z",
          "status": "operational",
          "responseTime": 486,
          "statusCode": 301
        },
        {
          "timestamp": "2025-10-25T23:59:12.498Z",
          "status": "operational",
          "responseTime": 346,
          "statusCode": 301
        },
        {
          "timestamp": "2025-10-26T02:02:47.589Z",
          "status": "operational",
          "responseTime": 506,
          "statusCode": 301
        },
        {
          "timestamp": "2025-10-26T03:15:21.899Z",
          "status": "operational",
          "responseTime": 680,
          "statusCode": 301
        },
        {
          "timestamp": "2025-10-26T03:48:23.583Z",
          "status": "operational",
          "responseTime": 411,
          "statusCode": 301
        },
        {
          "timestamp": "2025-10-26T03:58:58.162Z",
          "status": "operational",
          "responseTime": 387,
          "statusCode": 301
        },
        {
          "timestamp": "2025-10-26T04:27:13.425Z",
          "status": "operational",
          "responseTime": 525,
          "statusCode": 301
        },
        {
          "timestamp": "2025-10-26T04:42:06.079Z",
          "status": "operational",
          "responseTime": 422,
          "statusCode": 301
        },
        {
          "timestamp": "2025-10-26T04:51:07.018Z",
          "status": "operational",
          "responseTime": 566,
          "statusCode": 301
        },
        {
          "timestamp": "2025-10-26T04:59:40.813Z",
          "status": "operational",
          "responseTime": 344,
          "statusCode": 301
        }
      ]
    }
  }
}