{
  "lastUpdate": "2025-10-22T17:50:50.733Z",
  "services": {
    "canary-cloud": {
      "status": "down",
      "lastChecked": "2025-10-22T17:50:50.733Z",
      "responseTime": 10198,
      "recentChecks": [
        {
          "timestamp": "2025-10-22T14:46:31.377Z",
          "status": "down",
          "responseTime": 10259
        },
        {
          "timestamp": "2025-10-22T14:57:02.920Z",
          "status": "down",
          "responseTime": 10274
        },
        {
          "timestamp": "2025-10-22T15:21:04.901Z",
          "status": "down",
          "responseTime": 10281
        },
        {
          "timestamp": "2025-10-22T15:39:14.035Z",
          "status": "down",
          "responseTime": 10332
        },
        {
          "timestamp": "2025-10-22T15:48:44.527Z",
          "status": "down",
          "responseTime": 10186
        },
        {
          "timestamp": "2025-10-22T15:58:23.753Z",
          "status": "down",
          "responseTime": 11737
        },
        {
          "timestamp": "2025-10-22T16:31:25.587Z",
          "status": "down",
          "responseTime": 10177
        },
        {
          "timestamp": "2025-10-22T16:52:22.113Z",
          "status": "down",
          "responseTime": 10227
        },
        {
          "timestamp": "2025-10-22T17:09:30.745Z",
          "status": "down",
          "responseTime": 10224
        },
        {
          "timestamp": "2025-10-22T17:28:45.734Z",
          "status": "down",
          "responseTime": 10214
        },
        {
          "timestamp": "2025-10-22T17:41:27.080Z",
          "status": "down",
          "responseTime": 10275
        },
        {
          "timestamp": "2025-10-22T17:50:50.733Z",
          "status": "down",
          "responseTime": 10198
        }
      ]
    },
    "character-wiki": {
      "status": "operational",
      "lastChecked": "2025-10-22T17:50:50.733Z",
      "responseTime": 366,
      "recentChecks": [
        {
          "timestamp": "2025-10-22T14:46:31.377Z",
          "status": "operational",
          "responseTime": 477,
          "statusCode": 301
        },
        {
          "timestamp": "2025-10-22T14:57:02.920Z",
          "status": "operational",
          "responseTime": 705,
          "statusCode": 301
        },
        {
          "timestamp": "2025-10-22T15:21:04.901Z",
          "status": "operational",
          "responseTime": 475,
          "statusCode": 301
        },
        {
          "timestamp": "2025-10-22T15:39:14.035Z",
          "status": "operational",
          "responseTime": 601,
          "statusCode": 301
        },
        {
          "timestamp": "2025-10-22T15:48:44.527Z",
          "status": "operational",
          "responseTime": 437,
          "statusCode": 301
        },
        {
          "timestamp": "2025-10-22T15:58:23.753Z",
          "status": "operational",
          "responseTime": 384,
          "statusCode": 301
        },
        {
          "timestamp": "2025-10-22T16:31:25.587Z",
          "status": "operational",
          "responseTime": 445,
          "statusCode": 301
        },
        {
          "timestamp": "2025-10-22T16:52:22.113Z",
          "status": "operational",
          "responseTime": 603,
          "statusCode": 301
        },
        {
          "timestamp": "2025-10-22T17:09:30.745Z",
          "status": "operational",
          "responseTime": 476,
          "statusCode": 301
        },
        {
          "timestamp": "2025-10-22T17:28:45.734Z",
          "status": "operational",
          "responseTime": 506,
          "statusCode": 301
        },
        {
          "timestamp": "2025-10-22T17:41:27.080Z",
          "status": "operational",
          "responseTime": 410,
          "statusCode": 301
        },
        {
          "timestamp": "2025-10-22T17:50:50.733Z",
          "status": "operational",
          "responseTime": 366,
          "statusCode": 301
        }
      ]
    }
  }
}