{
  "lastUpdate": "2025-11-11T05:38:47.478Z",
  "services": {
    "canary-cloud": {
      "status": "operational",
      "lastChecked": "2025-11-11T05:38:47.478Z",
      "responseTime": 412,
      "recentChecks": [
        {
          "timestamp": "2025-11-10T23:32:10.312Z",
          "status": "operational",
          "responseTime": 275,
          "statusCode": 200
        },
        {
          "timestamp": "2025-11-10T23:43:07.650Z",
          "status": "operational",
          "responseTime": 554,
          "statusCode": 200
        },
        {
          "timestamp": "2025-11-10T23:52:27.594Z",
          "status": "operational",
          "responseTime": 196,
          "statusCode": 200
        },
        {
          "timestamp": "2025-11-11T00:50:05.677Z",
          "status": "operational",
          "responseTime": 369,
          "statusCode": 200
        },
        {
          "timestamp": "2025-11-11T02:25:11.652Z",
          "status": "operational",
          "responseTime": 190,
          "statusCode": 200
        },
        {
          "timestamp": "2025-11-11T03:33:23.301Z",
          "status": "operational",
          "responseTime": 309,
          "statusCode": 200
        },
        {
          "timestamp": "2025-11-11T03:59:13.964Z",
          "status": "operational",
          "responseTime": 320,
          "statusCode": 200
        },
        {
          "timestamp": "2025-11-11T04:31:45.518Z",
          "status": "operational",
          "responseTime": 254,
          "statusCode": 200
        },
        {
          "timestamp": "2025-11-11T04:47:36.809Z",
          "status": "operational",
          "responseTime": 251,
          "statusCode": 200
        },
        {
          "timestamp": "2025-11-11T04:56:43.348Z",
          "status": "operational",
          "responseTime": 260,
          "statusCode": 200
        },
        {
          "timestamp": "2025-11-11T05:20:24.454Z",
          "status": "operational",
          "responseTime": 264,
          "statusCode": 200
        },
        {
          "timestamp": "2025-11-11T05:38:47.478Z",
          "status": "operational",
          "responseTime": 412,
          "statusCode": 200
        }
      ]
    },
    "character-wiki": {
      "status": "operational",
      "lastChecked": "2025-11-11T05:38:47.478Z",
      "responseTime": 542,
      "recentChecks": [
        {
          "timestamp": "2025-11-10T23:32:10.312Z",
          "status": "operational",
          "responseTime": 371,
          "statusCode": 301
        },
        {
          "timestamp": "2025-11-10T23:43:07.650Z",
          "status": "operational",
          "responseTime": 668,
          "statusCode": 301
        },
        {
          "timestamp": "2025-11-10T23:52:27.594Z",
          "status": "operational",
          "responseTime": 467,
          "statusCode": 301
        },
        {
          "timestamp": "2025-11-11T00:50:05.677Z",
          "status": "operational",
          "responseTime": 2456,
          "statusCode": 301
        },
        {
          "timestamp": "2025-11-11T02:25:11.652Z",
          "status": "operational",
          "responseTime": 515,
          "statusCode": 301
        },
        {
          "timestamp": "2025-11-11T03:33:23.301Z",
          "status": "operational",
          "responseTime": 423,
          "statusCode": 301
        },
        {
          "timestamp": "2025-11-11T03:59:13.964Z",
          "status": "operational",
          "responseTime": 555,
          "statusCode": 301
        },
        {
          "timestamp": "2025-11-11T04:31:45.518Z",
          "status": "operational",
          "responseTime": 371,
          "statusCode": 301
        },
        {
          "timestamp": "2025-11-11T04:47:36.809Z",
          "status": "operational",
          "responseTime": 561,
          "statusCode": 301
        },
        {
          "timestamp": "2025-11-11T04:56:43.348Z",
          "status": "operational",
          "responseTime": 755,
          "statusCode": 301
        },
        {
          "timestamp": "2025-11-11T05:20:24.454Z",
          "status": "operational",
          "responseTime": 384,
          "statusCode": 301
        },
        {
          "timestamp": "2025-11-11T05:38:47.478Z",
          "status": "operational",
          "responseTime": 542,
          "statusCode": 301
        }
      ]
    }
  }
}